django_khalti_integration-0.0.4.dist-info/licenses/LICENSE
khalti/__init__.py
khalti/apps.py
khalti/client.py
khalti/config.py
khalti/responses.py
khalti/schemas.py
khalti/settings.py
django_khalti_integration-0.0.4.dist-info/METADATA
django_khalti_integration-0.0.4.dist-info/WHEEL
django_khalti_integration-0.0.4.dist-info/top_level.txt
django_khalti_integration-0.0.4.dist-info/RECORD
