Metadata-Version: 2.4
Name: django-khalti-integration
Version: 0.0.4
Summary: A Django integration for Khalti Payment Gateway in Nepal.
Author-email: Utsav Gurmachhan Magar <me@ryuuzu.xyz>
Project-URL: Homepage, https://github.com/ryuuzu-xyz/django-khalti-integration
Classifier: Framework :: Django
Classifier: Programming Language :: Python :: 3
Classifier: License :: OSI Approved :: MIT License
Classifier: Operating System :: OS Independent
Requires-Python: >=3.8
License-File: LICENSE
Requires-Dist: django>=3.2
Requires-Dist: pydantic>=2.10.6
Requires-Dist: requests>=2.25.1
Dynamic: license-file
